CIMAP/__init__.py
CIMAP/act_plot.py
CIMAP/algorithm_output.py
CIMAP/clusters_plot.py
CIMAP/cuts.py
CIMAP/data_reading.py
CIMAP/dendro_plot.py
CIMAP/dendrograms.py
CIMAP/find_cuts.py
CIMAP/get_target_graph.py
CIMAP/intervals.py
CIMAP/modality_distribution.py
CIMAP/modality_division.py
CIMAP/remove_add_ints.py
CIMAP/result_saver.py
CIMAP/run_algorithm.py
CIMAP/utils.py
CIMAP-1.1.1.dist-info/LICENSE.md
CIMAP-1.1.1.dist-info/METADATA
CIMAP-1.1.1.dist-info/WHEEL
CIMAP-1.1.1.dist-info/top_level.txt
CIMAP-1.1.1.dist-info/RECORD
